gremlin/config/DataStax.yaml
gremlin/config/Neo4j.yaml
gremlin/config/OrientDB.yaml
gremlin/config/TinkerGraph.yaml
gremlin/config/server.yaml
gremlin/data/air-routes-small.xml
gremlin/data/tinkerpop-modern.xml
gremlin/__init__.py
gremlin/draw.py
gremlin/examples.py
gremlin/remote.py
gremlin_python_tutorial-0.0.8.dist-info/METADATA
gremlin_python_tutorial-0.0.8.dist-info/WHEEL
gremlin_python_tutorial-0.0.8.dist-info/licenses/LICENSE
gremlin_python_tutorial-0.0.8.dist-info/RECORD
