Metadata-Version: 2.1
Name: gremlin-python-tutorial
Version: 0.0.8
Project-URL: Home, https://github.com/WolfgangFahl/gremlin-python-tutorial
Project-URL: Documentation, https://wiki.bitplan.com/index.php/Gremlin_python
Project-URL: Source, https://github.com/WolfgangFahl/gremlin-python-tutorial
Author-email: Wolfgang Fahl <wf@bitplan.com>, Julian Vollmer <julian.vollmer@rwth-aachen.de>
Maintainer-email: Wolfgang Fahl <wf@bitplan.com>, Julian Vollmer <julian.vollmer@rwth-aachen.de>
License:                                  Apache License
License-File: LICENSE
Classifier: Development Status :: 4 - Beta
Classifier: Environment :: Web Environment
Classifier: Intended Audience :: Developers
Classifier: Intended Audience :: Science/Research
Classifier: License :: OSI Approved :: Apache Software License
Classifier: Operating System :: OS Independent
Classifier: Programming Language :: Python :: 3 :: Only
Classifier: Programming Language :: Python :: 3.8
Classifier: Programming Language :: Python :: 3.9
Classifier: Programming Language :: Python :: 3.10
Classifier: Programming Language :: Python :: 3.11
Classifier: Topic :: Software Development
Requires-Python: >=3.8
Requires-Dist: aenum>=3.1
Requires-Dist: graphviz>=0.20.1
Requires-Dist: gremlinpython>=3.7.0
Requires-Dist: pyyaml>=6.0
Provides-Extra: test
Requires-Dist: green; extra == 'test'
